opentelemetry/resource/detector/azure/app_service.py
opentelemetry/resource/detector/azure/version.py
opentelemetry/resource/detector/azure/vm.py
opentelemetry_resource_detector_azure-0.1.4.dist-info/METADATA
opentelemetry_resource_detector_azure-0.1.4.dist-info/WHEEL
opentelemetry_resource_detector_azure-0.1.4.dist-info/entry_points.txt
opentelemetry_resource_detector_azure-0.1.4.dist-info/licenses/LICENSE
opentelemetry_resource_detector_azure-0.1.4.dist-info/RECORD
