Metadata-Version: 2.3
Name: opentelemetry-resource-detector-azure
Version: 0.1.4
Summary: Azure Resource Detector for OpenTelemetry
Project-URL: Homepage, https://github.com/open-telemetry/opentelemetry-python-contrib/tree/main/resource/opentelemetry-resource-detector-azure
Author-email: OpenTelemetry Authors <cncf-opentelemetry-contributors@lists.cncf.io>
License-Expression: Apache-2.0
License-File: LICENSE
Classifier: Development Status :: 4 - Beta
Classifier: Intended Audience :: Developers
Classifier: License :: OSI Approved :: Apache Software License
Classifier: Programming Language :: Python
Classifier: Programming Language :: Python :: 3
Classifier: Programming Language :: Python :: 3.8
Classifier: Programming Language :: Python :: 3.9
Classifier: Programming Language :: Python :: 3.10
Classifier: Programming Language :: Python :: 3.11
Requires-Python: >=3.8
Requires-Dist: opentelemetry-sdk~=1.21
